.testr.conf
.travis.yml
AUTHORS
ChangeLog
LICENSE
Makefile
README.rst
circle.yml
requirements.txt
setup.cfg
setup.py
tox.ini
libindic/soundex/__init__.py
libindic/soundex/templates/libindic.soundex.html
libindic_soundex.egg-info/PKG-INFO
libindic_soundex.egg-info/SOURCES.txt
libindic_soundex.egg-info/dependency_links.txt
libindic_soundex.egg-info/namespace_packages.txt
libindic_soundex.egg-info/not-zip-safe
libindic_soundex.egg-info/pbr.json
libindic_soundex.egg-info/top_level.txt
tests/__init__.py
tests/test_soundex.py